gym_foo/__init__.py
gym_foo/envs/__init__.py
gym_foo/envs/foo_env.py
ksh_test_foo-0.0.1.dist-info/METADATA
ksh_test_foo-0.0.1.dist-info/WHEEL
ksh_test_foo-0.0.1.dist-info/top_level.txt
ksh_test_foo-0.0.1.dist-info/RECORD
